mlops_utils/__init__.py
mlops_utils/mlflow_logger/__init__.py
mlops_utils/mlflow_logger/pytorch.py
mlops_utils/mlflow_logger/sklearn.py
mlops_utils/test/__init__.py
mlops_utils/test/mlflow/__init__.py
mlops_utils/test/mlflow/test_decorator.py
mlops_utils-0.0.2.dist-info/METADATA
mlops_utils-0.0.2.dist-info/WHEEL
mlops_utils-0.0.2.dist-info/top_level.txt
mlops_utils-0.0.2.dist-info/RECORD
